datastore/__init__.py
datastore/apps.py
datastore/fields.py
datastore/managers.py
datastore/models.py
datastore/permissions.py
datastore/serializers.py
datastore/tests.py
datastore/urls.py
datastore/views.py
datastore/migrations/0001_initial.py
datastore/migrations/0002_auto_20181024_1609.py
datastore/migrations/0003_auto_20181120_1059.py
datastore/migrations/0004_relateddocument_properties.py
datastore/migrations/__init__.py
test_project/__init__.py
test_project/settings.py
test_project/urls.py
test_project/wsgi.py
django_datastore-0.1.1.dist-info/LICENSE
django_datastore-0.1.1.dist-info/METADATA
django_datastore-0.1.1.dist-info/WHEEL
django_datastore-0.1.1.dist-info/top_level.txt
django_datastore-0.1.1.dist-info/RECORD
